dir_wand/_version.py
dir_wand/art.py
dir_wand/command_runner.py
dir_wand/directory.py
dir_wand/file.py
dir_wand/logger.py
dir_wand/main.py
dir_wand/parser.py
dir_wand/swapfile.py
dir_wand/template.py
dir_wand/utils.py
dir_wand-1.0.1.dist-info/LICENSE
dir_wand-1.0.1.dist-info/METADATA
dir_wand-1.0.1.dist-info/WHEEL
dir_wand-1.0.1.dist-info/entry_points.txt
dir_wand-1.0.1.dist-info/top_level.txt
dir_wand-1.0.1.dist-info/RECORD
