Metadata-Version: 2.1
Name: dir-wand
Version: 1.0.1
Summary: A CLI tool for making many directories from a template automagically.
Author-email: Will Roper <w.roper@sussex.ac.uk>
License: GNU GENERAL PUBLIC LICENSE
Project-URL: Homepage, https://github.com/WillJRoper/dir-wand
Project-URL: Source, https://github.com/WillJRoper/dir-wand
Project-URL: Tracker, https://github.com/WillJRoper/dir-wand/issues
Classifier: Development Status :: 4 - Beta
Classifier: Intended Audience :: Developers
Classifier: Intended Audience :: End Users/Desktop
Classifier: Intended Audience :: Science/Research
Classifier: License :: OSI Approved :: GNU General Public License (GPL)
Classifier: Programming Language :: Python
Classifier: Programming Language :: Python :: 3
Classifier: Programming Language :: Python :: 3.8
Classifier: Programming Language :: Python :: 3.9
Classifier: Programming Language :: Python :: 3.10
Classifier: Programming Language :: Python :: 3.11
Classifier: Operating System :: OS Independent
Classifier: Topic :: Software Development :: Build Tools
Classifier: Topic :: Utilities
Requires-Python: >=3.8
License-File: LICENSE
Requires-Dist: pyyaml
Provides-Extra: dev
Requires-Dist: ruff >=0.3.0 ; extra == 'dev'
